README.md
setup.py
RestrictedBoosting/RestrictedBoostClassifier.py
RestrictedBoosting/__init__.py
RestrictedEmsemble.egg-info/PKG-INFO
RestrictedEmsemble.egg-info/SOURCES.txt
RestrictedEmsemble.egg-info/dependency_links.txt
RestrictedEmsemble.egg-info/requires.txt
RestrictedEmsemble.egg-info/top_level.txt