Metadata-Version: 1.0
Name: RestrictedEmsemble
Version: 4.4.5
Summary: A Boosting Frame for Classifier
Home-page: https://github.com/LiangjunFeng/RestrictedEmsemble
Author: LiangjunFeng
Author-email: zhumavip@163.com
License: MIT Licence
Keywords: pip,Classifier,EnsembleLearning,RestrctedBoosting,Tree
Platform: any
